COPYING.LGPL
LICENSE
MANIFEST.in
README.rst
casuarius.cpp
casuarius.pyx
cysw_support.cc
cysw_support.h
cassowary/AbstractVariable.cc
cassowary/AbstractVariable.h
cassowary/Cassowary.h
cassowary/Cl.h
cassowary/Constraint.cc
cassowary/Constraint.h
cassowary/ConstraintHash.h
cassowary/Constraint_P.h
cassowary/DummyVariable.cc
cassowary/DummyVariable.h
cassowary/EditConstraint.h
cassowary/EditOrStayConstraint.h
cassowary/Errors.cc
cassowary/Errors.h
cassowary/FDVariable.cc
cassowary/FDVariable.h
cassowary/FloatVariable.cc
cassowary/FloatVariable.h
cassowary/LinearConstraint.h
cassowary/LinearEquation.h
cassowary/LinearExpression.cc
cassowary/LinearExpression.h
cassowary/LinearExpression_fwd.h
cassowary/LinearInequality.h
cassowary/Map.h
cassowary/ObjectiveVariable.h
cassowary/Point.h
cassowary/Set.h
cassowary/SimplexSolver.cc
cassowary/SimplexSolver.h
cassowary/SlackVariable.cc
cassowary/SlackVariable.h
cassowary/Solver.cc
cassowary/Solver.h
cassowary/StayConstraint.h
cassowary/Strength.cc
cassowary/Strength.h
cassowary/SymbolicWeight.cc
cassowary/SymbolicWeight.h
cassowary/Tableau.cc
cassowary/Tableau.h
cassowary/Typedefs.h
cassowary/Variable.cc
cassowary/Variable.h
cassowary/config-inline.h
cassowary/config.h
cassowary/config.h.in
cassowary/debug.h
cassowary/my/refcnt.h
cassowary/my/refcntp.h
casuarius.egg-info/PKG-INFO
casuarius.egg-info/SOURCES.txt
casuarius.egg-info/dependency_links.txt
casuarius.egg-info/top_level.txt