Metadata-Version: 1.0
Name: casuarius
Version: 1.0b1
Summary: Cython bindings for the Cassowary constraint solver.
Home-page: https://github.com/enthought/casuarius
Author: Robert Kern
Author-email: rkern@enthought.com
License: UNKNOWN
Platform: UNKNOWN
Classifier: Development Status :: 4 - Beta
Classifier: Intended Audience :: Developers
Classifier: License :: OSI Approved :: GNU Library or Lesser General Public License (LGPL)
Classifier: Operating System :: OS Independent
Classifier: Programming Language :: C++
Classifier: Programming Language :: Python
Classifier: Topic :: Software Development :: User Interfaces
